[{"name":"sql.active_record","payload":{"sql":"SELECT  \"users\".* FROM \"users\"  WHERE \"users\".\"id\" = 1  ORDER BY \"users\".\"id\" ASC LIMIT 1","name":"User Load","connection_id":69858660742260,"statement_name":null,"binds":[]},"time":"2015-04-30T17:16:25.510+05:30","transaction_id":"0342fbc283f7763ff570","end":"2015-04-30T17:16:25.522+05:30","children":[],"duration":12.522105999999999},{"name":"sql.active_record","payload":{"sql":"SELECT  \"events\".* FROM \"events\"  WHERE \"events\".\"id\" = $1 LIMIT 1","name":"Event Load","connection_id":69858660742260,"statement_name":"a2","binds":[[{"oid_type":{},"array":false,"name":"id","sql_type":"integer","null":false,"limit":null,"precision":null,"scale":null,"type":"integer","default":null,"default_function":"nextval('events_id_seq'::regclass)","primary":true,"coder":null},4]],"line":31,"filename":"/home/sayyad/Desktop/cosmicventplanner/app/controllers/events_controller.rb","method":"set_event"},"time":"2015-04-30T17:16:25.542+05:30","transaction_id":"0342fbc283f7763ff570","end":"2015-04-30T17:16:25.547+05:30","children":[],"duration":4.255635},{"name":"sql.active_record","payload":{"sql":"BEGIN","name":null,"connection_id":69858660742260,"statement_name":null,"binds":[],"line":21,"filename":"/home/sayyad/Desktop/cosmicventplanner/app/controllers/events_controller.rb","method":"update"},"time":"2015-04-30T17:16:25.567+05:30","transaction_id":"0342fbc283f7763ff570","end":"2015-04-30T17:16:25.569+05:30","children":[],"duration":1.471444},{"name":"sql.active_record","payload":{"sql":"              SELECT COUNT(*)\n              FROM pg_class c\n              LEFT JOIN pg_namespace n ON n.oid = c.relnamespace\n              WHERE c.relkind in ('v','r')\n              AND c.relname = 'events'\n              AND n.nspname = ANY (current_schemas(false))\n","name":"SCHEMA","connection_id":69858660742260,"statement_name":null,"binds":[],"line":21,"filename":"/home/sayyad/Desktop/cosmicventplanner/app/controllers/events_controller.rb","method":"update"},"time":"2015-04-30T17:16:25.597+05:30","transaction_id":"0342fbc283f7763ff570","end":"2015-04-30T17:16:25.602+05:30","children":[],"duration":5.128673},{"name":"sql.active_record","payload":{"sql":"UPDATE \"events\" SET \"all_day\" = $1, \"updated_at\" = $2 WHERE \"events\".\"id\" = 4","name":"SQL","connection_id":69858660742260,"statement_name":"a3","binds":[[{"oid_type":{},"array":false,"name":"all_day","sql_type":"boolean","null":false,"limit":null,"precision":null,"scale":null,"type":"boolean","default":false,"default_function":null,"primary":false,"coder":null},"t"],[{"oid_type":{},"array":false,"name":"updated_at","sql_type":"timestamp without time zone","null":false,"limit":null,"precision":null,"scale":null,"type":"datetime","default":null,"default_function":null,"primary":false,"coder":null},"2015-04-30 11:46:25.593778"]],"line":21,"filename":"/home/sayyad/Desktop/cosmicventplanner/app/controllers/events_controller.rb","method":"update"},"time":"2015-04-30T17:16:25.623+05:30","transaction_id":"0342fbc283f7763ff570","end":"2015-04-30T17:16:25.625+05:30","children":[],"duration":2.542048},{"name":"sql.active_record","payload":{"sql":"COMMIT","name":null,"connection_id":69858660742260,"statement_name":null,"binds":[],"line":21,"filename":"/home/sayyad/Desktop/cosmicventplanner/app/controllers/events_controller.rb","method":"update"},"time":"2015-04-30T17:16:25.642+05:30","transaction_id":"0342fbc283f7763ff570","end":"2015-04-30T17:16:25.653+05:30","children":[],"duration":10.804486},{"name":"render_partial.action_view","payload":{"identifier":"/home/sayyad/Desktop/cosmicventplanner/app/views/events/_save.js.haml"},"time":"2015-04-30T17:16:25.703+05:30","transaction_id":"b9edc9906e1be5fd4fb8","end":"2015-04-30T17:16:25.707+05:30","children":[],"duration":3.600926},{"name":"render_template.action_view","payload":{"identifier":"/home/sayyad/Desktop/cosmicventplanner/app/views/events/update.js.haml","layout":null},"time":"2015-04-30T17:16:25.685+05:30","transaction_id":"b9edc9906e1be5fd4fb8","end":"2015-04-30T17:16:25.710+05:30","children":[],"duration":24.946289},{"name":"process_action.action_controller","payload":{"controller":"EventsController","action":"update","params":{"utf8":"✓","_method":"patch","event":{"name":"hashmi","phone":"9885582480","budget":"3Lakhs","start":"April 30 2015  3:59 PM","description":"i can do this","finish":"May 02 2015  3:59 PM","status":"volatile","site_id":"6","all_day":"1"},"commit":"Submit","action":"update","controller":"events","id":"4"},"format":"js","method":"POST","path":"/events/4","status":200,"view_runtime":54.625872002361575,"db_runtime":24.007996},"time":"2015-04-30T17:16:25.499+05:30","transaction_id":"b9edc9906e1be5fd4fb8","end":"2015-04-30T17:16:25.714+05:30","children":[],"duration":214.932943}]